{
  "@type" : "TEMPLATE",
  "uid" : "4e8a3e33-c127-467e-b57f-0b9acc0deaf7",
  "description" : {
    "@type" : "RESOURCE_DESCRIPTION",
    "originalAuthor" : {
      "date" : "2022-11-18"
    },
    "otherContributors" : [ ],
    "lifecycleState" : {
      "codeString" : "unmanaged"
    },
    "ipAcknowledgements" : { },
    "references" : { },
    "conversionDetails" : { },
    "otherDetails" : {
      "licence" : "This work is licensed under the Creative Commons Attribution-ShareAlike 4.0 International License. To view a copy of this license, visit http://creativecommons.org/licenses/by-sa/4.0/.",
      "custodian_organisation" : "openEHR Foundation",
      "original_namespace" : "org.openehr",
      "original_publisher" : "openEHR Foundation",
      "custodian_namespace" : "org.openehr",
      "MD5-CAM-1.0.1" : "3e44fb6ac8f3dc58f6ea0ff5f7bbd5b7",
      "PARENT:MD5-CAM-1.0.1" : "8FE80F3E80C594AAF99D3BA540A53D73",
      "sem_ver" : "0.2.0",
      "build_uid" : "8380597c-6c0a-4b35-b655-17c47c6020db"
    },
    "details" : {
      "de" : {
        "@type" : "RESOURCE_DESCRIPTION_ITEM",
        "language" : {
          "terminologyId" : {
            "value" : "ISO_639-1"
          },
          "codeString" : "de"
        },
        "keywords" : [ ],
        "originalResourceUri" : { },
        "otherDetails" : { }
      },
      "sv" : {
        "@type" : "RESOURCE_DESCRIPTION_ITEM",
        "language" : {
          "terminologyId" : {
            "value" : "ISO_639-1"
          },
          "codeString" : "sv"
        },
        "keywords" : [ ],
        "originalResourceUri" : { },
        "otherDetails" : { }
      },
      "ru" : {
        "@type" : "RESOURCE_DESCRIPTION_ITEM",
        "language" : {
          "terminologyId" : {
            "value" : "ISO_639-1"
          },
          "codeString" : "ru"
        },
        "keywords" : [ ],
        "originalResourceUri" : { },
        "otherDetails" : { }
      },
      "nb" : {
        "@type" : "RESOURCE_DESCRIPTION_ITEM",
        "language" : {
          "terminologyId" : {
            "value" : "ISO_639-1"
          },
          "codeString" : "nb"
        },
        "keywords" : [ ],
        "originalResourceUri" : { },
        "otherDetails" : { }
      },
      "es-ar" : {
        "@type" : "RESOURCE_DESCRIPTION_ITEM",
        "language" : {
          "terminologyId" : {
            "value" : "ISO_639-1"
          },
          "codeString" : "es-ar"
        },
        "keywords" : [ ],
        "originalResourceUri" : { },
        "otherDetails" : { }
      },
      "pt-br" : {
        "@type" : "RESOURCE_DESCRIPTION_ITEM",
        "language" : {
          "terminologyId" : {
            "value" : "ISO_639-1"
          },
          "codeString" : "pt-br"
        },
        "keywords" : [ ],
        "originalResourceUri" : { },
        "otherDetails" : { }
      },
      "en" : {
        "@type" : "RESOURCE_DESCRIPTION_ITEM",
        "language" : {
          "terminologyId" : {
            "value" : "ISO_639-1"
          },
          "codeString" : "en"
        },
        "keywords" : [ ],
        "originalResourceUri" : { },
        "otherDetails" : { }
      },
      "sl" : {
        "@type" : "RESOURCE_DESCRIPTION_ITEM",
        "language" : {
          "terminologyId" : {
            "value" : "ISO_639-1"
          },
          "codeString" : "sl"
        },
        "keywords" : [ ],
        "originalResourceUri" : { },
        "otherDetails" : { }
      },
      "it" : {
        "@type" : "RESOURCE_DESCRIPTION_ITEM",
        "language" : {
          "terminologyId" : {
            "value" : "ISO_639-1"
          },
          "codeString" : "it"
        },
        "keywords" : [ ],
        "originalResourceUri" : { },
        "otherDetails" : { }
      },
      "fr" : {
        "@type" : "RESOURCE_DESCRIPTION_ITEM",
        "language" : {
          "terminologyId" : {
            "value" : "ISO_639-1"
          },
          "codeString" : "fr"
        },
        "keywords" : [ ],
        "originalResourceUri" : { },
        "otherDetails" : { }
      }
    }
  },
  "parentArchetypeId" : "openEHR-EHR-SECTION.adhoc.v1",
  "differential" : true,
  "archetypeId" : {
    "@type" : "ARCHETYPE_HRID",
    "value" : "openEHR-EHR-SECTION.osdi(ocular_surface_disease_index).v1"
  },
  "definition" : {
    "@type" : "C_COMPLEX_OBJECT",
    "rmTypeName" : "SECTION",
    "nodeId" : "at0000.1",
    "attributes" : [ {
      "@type" : "C_ATTRIBUTE",
      "rmAttributeName" : "items",
      "existence" : "0..1",
      "cardinality" : {
        "@type" : "CARDINALITY",
        "interval" : "1..*",
        "ordered" : false,
        "unique" : false
      },
      "children" : [ {
        "@type" : "C_ARCHETYPE_ROOT",
        "rmTypeName" : "OBSERVATION",
        "occurrences" : "0..1",
        "nodeId" : "at0.2",
        "attributes" : [ ],
        "attributeTuples" : [ ],
        "archetypeRef" : "openEHR-EHR-OBSERVATION.ovl-symptom_sign_screening-001.v1",
        "referenceType" : "archetypeOverlay"
      } ]
    } ],
    "attributeTuples" : [ ]
  },
  "terminology" : {
    "@type" : "ARCHETYPE_TERMINOLOGY",
    "conceptCode" : "at0000",
    "termDefinitions" : {
      "en" : {
        "at0000.1" : {
          "@type" : "ARCHETYPE_TERM",
          "code" : "at0000.1",
          "text" : "OSDI (Ocular Surface Disease Index)",
          "description" : "A generic section header which should be renamed in a template to suit a specific clinical context."
        }
      },
      "ru" : {
        "at0000.1" : {
          "@type" : "ARCHETYPE_TERM",
          "code" : "at0000.1",
          "text" : "заготовка заголовка (4)",
          "description" : "Образец заголовка раздела"
        }
      },
      "es-ar" : {
        "at0000.1" : {
          "@type" : "ARCHETYPE_TERM",
          "code" : "at0000.1",
          "text" : "Encabezado ad hoc (4)",
          "description" : "Un encabezado de sección de tipo genérico que será renombrado en una plantilla para su empleo en un contexto clínico específico."
        }
      },
      "sl" : {
        "at0000.1" : {
          "@type" : "ARCHETYPE_TERM",
          "code" : "at0000.1",
          "text" : "Naslov sekcije (4)",
          "description" : "Naslov sekcije"
        }
      },
      "nb" : {
        "at0000.1" : {
          "@type" : "ARCHETYPE_TERM",
          "code" : "at0000.1",
          "text" : "Templat-overskrift (4)",
          "description" : "En generisk seksjonsoverskrift som skal gis nytt navn i en templat for å passe i en gitt klinisk kontekst."
        }
      },
      "pt-br" : {
        "at0000.1" : {
          "@type" : "ARCHETYPE_TERM",
          "code" : "at0000.1",
          "text" : "Cabeçalho Ad hoc (4)",
          "description" : "Um cabeçalho de sessão genérico que deve ser renomeado no template para adequar-se a um contexto clínico específico."
        }
      },
      "sv" : {
        "at0000.1" : {
          "@type" : "ARCHETYPE_TERM",
          "code" : "at0000.1",
          "text" : "Rubrik (4)",
          "description" : "En allmän avsnittsrubrik som döps om i en openEHR-mall för att passa in i en specifik klinisk kontext."
        }
      },
      "de" : {
        "at0000.1" : {
          "@type" : "ARCHETYPE_TERM",
          "code" : "at0000.1",
          "text" : "Ad hoc Überschrift (4)",
          "description" : "Eine generische Abschnittsüberschrift eines Templates, welche entsprechend dem spezifischen klinischen Kontext umbenannt werden sollte."
        }
      },
      "it" : {
        "at0000.1" : {
          "@type" : "ARCHETYPE_TERM",
          "code" : "at0000.1",
          "text" : "Intestazione di sezione ad hoc (4)",
          "description" : "Un'intestazione di sezione generica che dovrebbe essere rinominata in un template per adattarsi ad uno specifico contesto clinico."
        }
      },
      "fr" : {
        "at0000.1" : {
          "@type" : "ARCHETYPE_TERM",
          "code" : "at0000.1",
          "text" : "Rubrique ad hoc (4)",
          "description" : "Un en-tête de section générique qui doit être renommé dans un modèle pour s'adapter à un contexte clinique spécifique."
        }
      }
    },
    "termBindings" : { },
    "terminologyExtracts" : { },
    "valueSets" : { }
  },
  "adlVersion" : "1.4",
  "buildUid" : "59e4ad83-0095-3933-a203-4965e3f8cc37",
  "rmName" : "openehr",
  "rmRelease" : "1.1.0",
  "generated" : true,
  "templateId" : "DM-PxMata-OSDI(OcularSurfaceDiseaseIndex)",
  "otherMetaData" : { },
  "templateOverlays" : [ {
    "@type" : "TEMPLATE_OVERLAY",
    "uid" : "a884ffa3-e193-4152-862d-29e3401c1d6f",
    "description" : {
      "@type" : "RESOURCE_DESCRIPTION",
      "originalAuthor" : { },
      "otherContributors" : [ ],
      "ipAcknowledgements" : { },
      "references" : { },
      "conversionDetails" : { },
      "otherDetails" : {
        "PARENT:MD5-CAM-1.0.1" : "D0E02DE26104C7DB2CB94198C5B658FE"
      },
      "details" : {
        "de" : {
          "@type" : "RESOURCE_DESCRIPTION_ITEM",
          "language" : {
            "terminologyId" : {
              "value" : "ISO_639-1"
            },
            "codeString" : "de"
          },
          "purpose" : "*To create a framework for recording answers about symptoms or signs, to the questions of a pre-defined screening questionnaire. (en)",
          "keywords" : [ "*screening, questionnaire, emotions, pain numbness vertigo (en)" ],
          "use" : "*Use to create a framework for recording answers to pre-defined screening questions about symptoms or signs.\r\n\r\nCommon use cases include, but are not limited to:\r\n- Systematic inquiry in any consultation, for example:\r\n--- Do you have headaches? Yes, No, Unknown.\r\n--- Have you had dizziness in the past four weeks? Yes, No, Unknown.\r\n- Specific questioning related to disease surveillance.\r\n\r\nThe semantics of this archetype are intentionally loose, and querying this archetype would normally only be useful or safe within the context of each specific template. In a template, each data element would usually be renamed to the specific question asked. Where value sets have been proposed for common use cases, these can be adapted for local use by using the 'text' choice to match each specific use case.\r\n\r\nThe EVENT structure from the reference model can be used to specify whether the questions relate to point in time or over a period of time. Use a separate instance of this archetype to distinguish between a questionnaire recording information about a symptom that has been present at any time in the past and information about a symptom within a specified time interval - for example the difference between \"\"Are you dizzy now?\" compared to \"Have you had any dizziness in the past 4 weeks?\r\n\r\nThe source of the information in a questionnaire response may vary in different contexts but can be specifically identified using the 'Information provider' element in the Reference Model.\r\n\r\nThis archetype has been designed to be used as a screening tool or to record simple questionnaire-format data for use in situations such as a disease registry. If the screening questionnaire identifies the presence of a symptom or sign, it is recommended that clinical system record and persist the specific details about the symptom or sign using the CLUSTER.symptom_sign archetype nested within the Additional details SLOT in this archetype. (en)",
          "misuse" : "*Not to be used to record details about the presence or absence of a symptom, outside of a screening context. Use CLUSTER.symptom_sign or CLUSTER.exclusion_symptom_sign for these purposes.\r\n\r\nNot to be used to record details about a simple selection list where a question may be recorded as either \"present\" or \"indeterminate\". Use OBSERVATION.selection_list for this purpose. (en)",
          "originalResourceUri" : { },
          "otherDetails" : { }
        },
        "sv" : {
          "@type" : "RESOURCE_DESCRIPTION_ITEM",
          "language" : {
            "terminologyId" : {
              "value" : "ISO_639-1"
            },
            "codeString" : "sv"
          },
          "purpose" : "*To create a framework for recording answers to pre-defined screening questions about symptoms or signs.(en)",
          "keywords" : [ "*screening, questionnaire, emotions, pain numbness vertigo (en)" ],
          "use" : "*Use to create a framework for recording answers to pre-defined screening questions about symptoms or signs.\r\n\r\nCommon use cases include, but are not limited to:\r\n- Systematic inquiry in any consultation, for example:\r\n--- Do you have headaches? Yes, No, Unknown.\r\n--- Have you had dizziness in the past four weeks? Yes, No, Unknown.\r\n- Specific questioning related to disease surveillance.\r\n\r\nThe semantics of this archetype are intentionally loose, and querying this archetype would normally only be useful or safe within the context of each specific template. In a template, each data element would usually be renamed to the specific question asked. Where value sets have been proposed for common use cases, these can be adapted for local use by using the 'text' choice to match each specific use case.\r\n\r\nThe EVENT structure from the reference model can be used to specify whether the questions relate to point in time or over a period of time. Use a separate instance of this archetype to distinguish between a questionnaire recording information about a symptom that has been present at any time in the past and information about a symptom within a specified time interval - for example the difference between \"\"Are you dizzy now?\" compared to \"Have you had any dizziness in the past 4 weeks?\r\n\r\nThe source of the information in a questionnaire response may vary in different contexts but can be specifically identified using the 'Information provider' element in the Reference Model.\r\n\r\nThis archetype has been designed to be used as a screening tool or to record simple questionnaire-format data for use in situations such as a disease registry. If the screening questionnaire identifies the presence of a symptom or sign, it is recommended that clinical system record and persist the specific details about the symptom or sign using the CLUSTER.symptom_sign archetype nested within the Additional details SLOT in this archetype. (en)",
          "misuse" : "*Not to be used to record details about the presence or absence of a symptom, outside of a screening context. Use CLUSTER.symptom_sign or CLUSTER.exclusion_symptom_sign for these purposes.\r\n\r\nNot to be used to record details about a simple selection list where a question may be recorded as either \"present\" or \"indeterminate\". Use OBSERVATION.selection_list for this purpose. (en)",
          "originalResourceUri" : { },
          "otherDetails" : { }
        },
        "fi" : {
          "@type" : "RESOURCE_DESCRIPTION_ITEM",
          "language" : {
            "terminologyId" : {
              "value" : "ISO_639-1"
            },
            "codeString" : "fi"
          },
          "purpose" : "*To create a framework for recording answers about symptoms or signs, to the questions of a pre-defined screening questionnaire. (en)",
          "keywords" : [ "*screening, questionnaire, emotions, pain numbness vertigo (en)" ],
          "use" : "*Use to create a framework for recording answers to pre-defined screening questions about symptoms or signs.\r\n\r\nCommon use cases include, but are not limited to:\r\n- Systematic inquiry in any consultation, for example:\r\n--- Do you have headaches? Yes, No, Unknown.\r\n--- Have you had dizziness in the past four weeks? Yes, No, Unknown.\r\n- Specific questioning related to disease surveillance.\r\n\r\nThe semantics of this archetype are intentionally loose, and querying this archetype would normally only be useful or safe within the context of each specific template. In a template, each data element would usually be renamed to the specific question asked. Where value sets have been proposed for common use cases, these can be adapted for local use by using the 'text' choice to match each specific use case.\r\n\r\nThe EVENT structure from the reference model can be used to specify whether the questions relate to point in time or over a period of time. Use a separate instance of this archetype to distinguish between a questionnaire recording information about a symptom that has been present at any time in the past and information about a symptom within a specified time interval - for example the difference between \"\"Are you dizzy now?\" compared to \"Have you had any dizziness in the past 4 weeks?\r\n\r\nThe source of the information in a questionnaire response may vary in different contexts but can be specifically identified using the 'Information provider' element in the Reference Model.\r\n\r\nThis archetype has been designed to be used as a screening tool or to record simple questionnaire-format data for use in situations such as a disease registry. If the screening questionnaire identifies the presence of a symptom or sign, it is recommended that clinical system record and persist the specific details about the symptom or sign using the CLUSTER.symptom_sign archetype nested within the Additional details SLOT in this archetype. (en)",
          "misuse" : "*Not to be used to record details about the presence or absence of a symptom, outside of a screening context. Use CLUSTER.symptom_sign or CLUSTER.exclusion_symptom_sign for these purposes.\r\n\r\nNot to be used to record details about a simple selection list where a question may be recorded as either \"present\" or \"indeterminate\". Use OBSERVATION.selection_list for this purpose. (en)",
          "originalResourceUri" : { },
          "otherDetails" : { }
        },
        "nb" : {
          "@type" : "RESOURCE_DESCRIPTION_ITEM",
          "language" : {
            "terminologyId" : {
              "value" : "ISO_639-1"
            },
            "codeString" : "nb"
          },
          "purpose" : "For å lage et rammeverk for registrering av svar på forhåndsdefinerte spørsmål om symptomer eller sykdomstegn.",
          "keywords" : [ "intervjuskjema, kartleggingskjema, spørreskjema, lidelse, plage, problem, ubehag, symptom, sykdomstegn, lyte, skavank" ],
          "use" : "Brukes for å lage et rammeverk for registrering av svar på forhåndsdefinerte spørsmål om symptomer eller sykdomstegn.\r\n\r\nVanlige bruksområder inkluderer, men er ikke begrenset til:\r\n- Systematiske spørsmål ved konsultasjoner, for eksempel:\r\n--- Har du hodepine? Ja, Nei, Usikker.\r\n--- Har du vært plaget med svimmelhet de siste fire ukene? Ja, Nei, Usikker.\r\n- Spesifikke spørsmål relatert til overvåkning av sykdommer.\r\n\r\nSemantikken til denne arketypen er med vilje løst definert, og spørringer etter data i denne arketypen vil normalt bare være hensiktsmessig eller sikkert i konteksten av det spesifikke templatet. I et templat vil hvert dataelement vanligvis døpes om til det (spesifikke) spørsmålet man ønsker svar på. Flere steder er det foreslått verdisett som passer til de vanligste bruksområder, men det er allikevel mulig å tilpasse/endre verdisett for lokal bruk ved å benytte de alternative datatypene DV_TEXT eller DV_BOOLEAN for å harmonere verdisettet til hvert enkelt brukstilfelle.\r\n\r\nEVENT-strukturen fra arketypens referansemodell kan brukes for å spesifisere om spørsmålene relateres til et tidspunkt eller til et tidsintervall.\r\nBruk egne instanser av denne arketypen for å skille mellom spørsmål om prosedyrer som er gjennomførte på et hvilket som helst tidspunkt og spørsmål om prosedyrer som er gjennomført i et tidsintervall. For eksempel; \"Har du hodepine?\" sammenlignet med \"Har du vært plaget med svimmelhet de siste fire ukene?\".\r\n\r\nKilden til informasjonen i et spørreskjema kan variere i ulike kontekster, men kan identifiseres spesifikt ved å benytte \"Information provider\" elementet i openEHR referansemodellen.\r\n\r\nDenne arketypen er laget for å bli brukt i et spørreskjema eller for å registrere enkle strukturerte data til for eksempel et sykdomsregister. Dersom det i spørreskjemaet identifiseres at et symptom eller sykdomstegn er tilstede, anbefales det at spesifikke detaljer om symptomet registreres og lagres i pasientjournalen i arketypen CLUSTER.symptom_sign (Symptom/Sykdomstegn) i SLOTet \"Ytterligere detaljer\" i denne arketypen.",
          "misuse" : "Brukes ikke for å registrere detaljer om tilstedeværelse eller fravær av et symptom utenfor konteksten av kartleggingen. Bruk arketypen CLUSTER.symptom_sign (Symptom/sykdomstegn) eller CLUSTER.exclusion_symptom_sign (Eksklusjon av et symptom) for dette formålet.\r\n\r\nBrukes ikke for å registrere detaljer om en enkel utvalgsliste der et spørsmål kan registreres som enten \"Tilstede\" eller \"Ubestemt\". Bruk arketypen OBSERVATION.selection_list for dette formålet.",
          "originalResourceUri" : { },
          "otherDetails" : { }
        },
        "en" : {
          "@type" : "RESOURCE_DESCRIPTION_ITEM",
          "language" : {
            "terminologyId" : {
              "value" : "ISO_639-1"
            },
            "codeString" : "en"
          },
          "purpose" : "To create a framework for recording answers to pre-defined screening questions about symptoms or signs.",
          "keywords" : [ "screening, questionnaire, complaint, symptom, disturbance, problem, discomfort, sign" ],
          "use" : "Use to create a framework for recording answers to pre-defined screening questions about symptoms or signs.\r\n\r\nCommon use cases include, but are not limited to:\r\n- Systematic inquiry in any consultation, for example:\r\n--- Do you have headaches? Yes, No, Unknown.\r\n--- Have you had dizziness in the past four weeks? Yes, No, Unknown.\r\n- Specific questioning related to disease surveillance.\r\n\r\nThe semantics of this archetype are intentionally loose, and querying this archetype would normally only be useful or safe within the context of each specific template. In a template, each data element would usually be renamed to the specific question asked. Where value sets have been proposed for common use cases, these can be adapted for local use by using the DV_TEXT or the DV_BOOLEAN datatypes choice to match each specific use case.\r\n\r\nThe EVENT structure from the reference model can be used to specify whether the questions relate to point in time or over a period of time. Use a separate instance of this archetype to distinguish between a questionnaire recording information about a symptom that has been present at any time in the past and information about a symptom within a specified time interval - for example the difference between \"\"Are you dizzy now?\" compared to \"Have you had any dizziness in the past 4 weeks?\r\n\r\nThe source of the information in a questionnaire response may vary in different contexts but can be specifically identified using the 'Information provider' element in the Reference Model.\r\n\r\nThis archetype has been designed to be used as a screening tool or to record simple questionnaire-format data for use in situations such as a disease registry. If the screening questionnaire identifies the presence of a symptom or sign, it is recommended that clinical system record and persist the specific details about the symptom or sign using the CLUSTER.symptom_sign archetype nested within the Additional details SLOT in this archetype.",
          "misuse" : "Not to be used to record details about the presence or absence of a symptom, outside of a screening context. Use CLUSTER.symptom_sign or CLUSTER.exclusion_symptom_sign for these purposes.\r\n\r\nNot to be used to record details about a simple selection list where a question may be recorded as either \"present\" or \"indeterminate\". Use OBSERVATION.selection_list for this purpose.",
          "originalResourceUri" : { },
          "otherDetails" : { }
        },
        "it" : {
          "@type" : "RESOURCE_DESCRIPTION_ITEM",
          "language" : {
            "terminologyId" : {
              "value" : "ISO_639-1"
            },
            "codeString" : "it"
          },
          "purpose" : "*To create a framework for recording answers about symptoms or signs, to the questions of a pre-defined screening questionnaire. (en)",
          "keywords" : [ "*screening, questionnaire, emotions, pain numbness vertigo (en)" ],
          "use" : "*Use to create a framework for recording answers to pre-defined screening questions about symptoms or signs.\r\n\r\nCommon use cases include, but are not limited to:\r\n- Systematic inquiry in any consultation, for example:\r\n--- Do you have headaches? Yes, No, Unknown.\r\n--- Have you had dizziness in the past four weeks? Yes, No, Unknown.\r\n- Specific questioning related to disease surveillance.\r\n\r\nThe semantics of this archetype are intentionally loose, and querying this archetype would normally only be useful or safe within the context of each specific template. In a template, each data element would usually be renamed to the specific question asked. Where value sets have been proposed for common use cases, these can be adapted for local use by using the 'text' choice to match each specific use case.\r\n\r\nThe EVENT structure from the reference model can be used to specify whether the questions relate to point in time or over a period of time. Use a separate instance of this archetype to distinguish between a questionnaire recording information about a symptom that has been present at any time in the past and information about a symptom within a specified time interval - for example the difference between \"\"Are you dizzy now?\" compared to \"Have you had any dizziness in the past 4 weeks?\r\n\r\nThe source of the information in a questionnaire response may vary in different contexts but can be specifically identified using the 'Information provider' element in the Reference Model.\r\n\r\nThis archetype has been designed to be used as a screening tool or to record simple questionnaire-format data for use in situations such as a disease registry. If the screening questionnaire identifies the presence of a symptom or sign, it is recommended that clinical system record and persist the specific details about the symptom or sign using the CLUSTER.symptom_sign archetype nested within the Additional details SLOT in this archetype. (en)",
          "misuse" : "*Not to be used to record details about the presence or absence of a symptom, outside of a screening context. Use CLUSTER.symptom_sign or CLUSTER.exclusion_symptom_sign for these purposes.\r\n\r\nNot to be used to record details about a simple selection list where a question may be recorded as either \"present\" or \"indeterminate\". Use OBSERVATION.selection_list for this purpose. (en)",
          "originalResourceUri" : { },
          "otherDetails" : { }
        }
      }
    },
    "parentArchetypeId" : "openEHR-EHR-OBSERVATION.symptom_sign_screening.v1",
    "differential" : true,
    "archetypeId" : {
      "@type" : "ARCHETYPE_HRID",
      "value" : "openEHR-EHR-OBSERVATION.ovl-symptom_sign_screening-001.v1"
    },
    "definition" : {
      "@type" : "C_COMPLEX_OBJECT",
      "rmTypeName" : "OBSERVATION",
      "nodeId" : "at0000.1",
      "attributes" : [ {
        "@type" : "C_ATTRIBUTE",
        "rmAttributeName" : "data",
        "children" : [ {
          "@type" : "C_COMPLEX_OBJECT",
          "rmTypeName" : "HISTORY",
          "nodeId" : "at0001",
          "attributes" : [ {
            "@type" : "C_ATTRIBUTE",
            "rmAttributeName" : "events",
            "children" : [ {
              "@type" : "C_COMPLEX_OBJECT",
              "rmTypeName" : "EVENT",
              "nodeId" : "at0002.1",
              "attributes" : [ {
                "@type" : "C_ATTRIBUTE",
                "rmAttributeName" : "data",
                "children" : [ {
                  "@type" : "C_COMPLEX_OBJECT",
                  "rmTypeName" : "ITEM_TREE",
                  "nodeId" : "at0003",
                  "attributes" : [ {
                    "@type" : "C_ATTRIBUTE",
                    "rmAttributeName" : "items",
                    "children" : [ {
                      "@type" : "C_COMPLEX_OBJECT",
                      "rmTypeName" : "ELEMENT",
                      "occurrences" : "0..0",
                      "nodeId" : "at0034.1",
                      "attributes" : [ ],
                      "attributeTuples" : [ ]
                    }, {
                      "@type" : "C_COMPLEX_OBJECT",
                      "rmTypeName" : "ELEMENT",
                      "occurrences" : "1..1",
                      "nodeId" : "at0028.1",
                      "attributes" : [ {
                        "@type" : "C_ATTRIBUTE",
                        "rmAttributeName" : "value",
                        "children" : [ {
                          "@type" : "C_COMPLEX_OBJECT",
                          "rmTypeName" : "DV_CODED_TEXT",
                          "attributes" : [ {
                            "@type" : "C_ATTRIBUTE",
                            "rmAttributeName" : "defining_code",
                            "children" : [ {
                              "@type" : "C_TERMINOLOGY_CODE",
                              "rmTypeName" : "TERMINOLOGY_CODE",
                              "occurrences" : "1..1",
                              "terminologyId" : {
                                "value" : "local_terms"
                              },
                              "constraint" : [ ],
                              "selectedTerminologies" : [ "local_terms" ],
                              "includedExternalTerminologyCodes" : [ {
                                "terminologyId" : "local_terms",
                                "code" : "0",
                                "value" : "Tidak Pernah"
                              }, {
                                "terminologyId" : "local_terms",
                                "code" : "1",
                                "value" : "Selalu sepanjang hari"
                              }, {
                                "terminologyId" : "local_terms",
                                "code" : "2",
                                "value" : "Sebagian besar hari"
                              }, {
                                "terminologyId" : "local_terms",
                                "code" : "3",
                                "value" : "Separuh Hari"
                              }, {
                                "terminologyId" : "local_terms",
                                "code" : "4",
                                "value" : "Kadang-kadang"
                              } ]
                            } ]
                          } ],
                          "attributeTuples" : [ ]
                        } ]
                      } ],
                      "attributeTuples" : [ ]
                    }, {
                      "@type" : "C_COMPLEX_OBJECT",
                      "rmTypeName" : "ELEMENT",
                      "occurrences" : "1..1",
                      "nodeId" : "at0028.2",
                      "attributes" : [ {
                        "@type" : "C_ATTRIBUTE",
                        "rmAttributeName" : "value",
                        "children" : [ {
                          "@type" : "C_COMPLEX_OBJECT",
                          "rmTypeName" : "DV_CODED_TEXT",
                          "attributes" : [ {
                            "@type" : "C_ATTRIBUTE",
                            "rmAttributeName" : "defining_code",
                            "children" : [ {
                              "@type" : "C_TERMINOLOGY_CODE",
                              "rmTypeName" : "TERMINOLOGY_CODE",
                              "occurrences" : "1..1",
                              "terminologyId" : {
                                "value" : "local_terms"
                              },
                              "constraint" : [ ],
                              "selectedTerminologies" : [ "local_terms" ],
                              "includedExternalTerminologyCodes" : [ {
                                "terminologyId" : "local_terms",
                                "code" : "0",
                                "value" : "Tidak Pernah"
                              }, {
                                "terminologyId" : "local_terms",
                                "code" : "1",
                                "value" : "Selalu sepanjang hari"
                              }, {
                                "terminologyId" : "local_terms",
                                "code" : "2",
                                "value" : "Sebagian besar hari"
                              }, {
                                "terminologyId" : "local_terms",
                                "code" : "3",
                                "value" : "Separuh Hari"
                              }, {
                                "terminologyId" : "local_terms",
                                "code" : "4",
                                "value" : "Kadang-kadang"
                              } ]
                            } ]
                          } ],
                          "attributeTuples" : [ ]
                        } ]
                      } ],
                      "attributeTuples" : [ ]
                    }, {
                      "@type" : "C_COMPLEX_OBJECT",
                      "rmTypeName" : "ELEMENT",
                      "occurrences" : "1..1",
                      "nodeId" : "at0028.3",
                      "attributes" : [ {
                        "@type" : "C_ATTRIBUTE",
                        "rmAttributeName" : "value",
                        "children" : [ {
                          "@type" : "C_COMPLEX_OBJECT",
                          "rmTypeName" : "DV_CODED_TEXT",
                          "attributes" : [ {
                            "@type" : "C_ATTRIBUTE",
                            "rmAttributeName" : "defining_code",
                            "children" : [ {
                              "@type" : "C_TERMINOLOGY_CODE",
                              "rmTypeName" : "TERMINOLOGY_CODE",
                              "occurrences" : "1..1",
                              "terminologyId" : {
                                "value" : "local_terms"
                              },
                              "constraint" : [ ],
                              "selectedTerminologies" : [ "local_terms" ],
                              "includedExternalTerminologyCodes" : [ {
                                "terminologyId" : "local_terms",
                                "code" : "0",
                                "value" : "Tidak Pernah"
                              }, {
                                "terminologyId" : "local_terms",
                                "code" : "1",
                                "value" : "Selalu sepanjang hari"
                              }, {
                                "terminologyId" : "local_terms",
                                "code" : "2",
                                "value" : "Sebagian besar hari"
                              }, {
                                "terminologyId" : "local_terms",
                                "code" : "3",
                                "value" : "Separuh Hari"
                              }, {
                                "terminologyId" : "local_terms",
                                "code" : "4",
                                "value" : "Kadang-kadang"
                              } ]
                            } ]
                          } ],
                          "attributeTuples" : [ ]
                        } ]
                      } ],
                      "attributeTuples" : [ ]
                    }, {
                      "@type" : "C_COMPLEX_OBJECT",
                      "rmTypeName" : "ELEMENT",
                      "occurrences" : "1..1",
                      "nodeId" : "at0028.4",
                      "attributes" : [ {
                        "@type" : "C_ATTRIBUTE",
                        "rmAttributeName" : "value",
                        "children" : [ {
                          "@type" : "C_COMPLEX_OBJECT",
                          "rmTypeName" : "DV_CODED_TEXT",
                          "attributes" : [ {
                            "@type" : "C_ATTRIBUTE",
                            "rmAttributeName" : "defining_code",
                            "children" : [ {
                              "@type" : "C_TERMINOLOGY_CODE",
                              "rmTypeName" : "TERMINOLOGY_CODE",
                              "occurrences" : "1..1",
                              "terminologyId" : {
                                "value" : "local_terms"
                              },
                              "constraint" : [ ],
                              "selectedTerminologies" : [ "local_terms" ],
                              "includedExternalTerminologyCodes" : [ {
                                "terminologyId" : "local_terms",
                                "code" : "0",
                                "value" : "Tidak Pernah"
                              }, {
                                "terminologyId" : "local_terms",
                                "code" : "1",
                                "value" : "Selalu sepanjang hari"
                              }, {
                                "terminologyId" : "local_terms",
                                "code" : "2",
                                "value" : "Sebagian besar hari"
                              }, {
                                "terminologyId" : "local_terms",
                                "code" : "3",
                                "value" : "Separuh Hari"
                              }, {
                                "terminologyId" : "local_terms",
                                "code" : "4",
                                "value" : "Kadang-kadang"
                              } ]
                            } ]
                          } ],
                          "attributeTuples" : [ ]
                        } ]
                      } ],
                      "attributeTuples" : [ ]
                    }, {
                      "@type" : "C_COMPLEX_OBJECT",
                      "rmTypeName" : "ELEMENT",
                      "occurrences" : "1..1",
                      "nodeId" : "at0028.5",
                      "attributes" : [ {
                        "@type" : "C_ATTRIBUTE",
                        "rmAttributeName" : "value",
                        "children" : [ {
                          "@type" : "C_COMPLEX_OBJECT",
                          "rmTypeName" : "DV_CODED_TEXT",
                          "attributes" : [ {
                            "@type" : "C_ATTRIBUTE",
                            "rmAttributeName" : "defining_code",
                            "children" : [ {
                              "@type" : "C_TERMINOLOGY_CODE",
                              "rmTypeName" : "TERMINOLOGY_CODE",
                              "occurrences" : "1..1",
                              "terminologyId" : {
                                "value" : "local_terms"
                              },
                              "constraint" : [ ],
                              "selectedTerminologies" : [ "local_terms" ],
                              "includedExternalTerminologyCodes" : [ {
                                "terminologyId" : "local_terms",
                                "code" : "0",
                                "value" : "Tidak Pernah"
                              }, {
                                "terminologyId" : "local_terms",
                                "code" : "1",
                                "value" : "Selalu sepanjang hari"
                              }, {
                                "terminologyId" : "local_terms",
                                "code" : "2",
                                "value" : "Sebagian besar hari"
                              }, {
                                "terminologyId" : "local_terms",
                                "code" : "3",
                                "value" : "Separuh Hari"
                              }, {
                                "terminologyId" : "local_terms",
                                "code" : "4",
                                "value" : "Kadang-kadang"
                              } ]
                            } ]
                          } ],
                          "attributeTuples" : [ ]
                        } ]
                      } ],
                      "attributeTuples" : [ ]
                    }, {
                      "@type" : "C_COMPLEX_OBJECT",
                      "rmTypeName" : "ELEMENT",
                      "occurrences" : "1..1",
                      "nodeId" : "at0028.6",
                      "attributes" : [ {
                        "@type" : "C_ATTRIBUTE",
                        "rmAttributeName" : "value",
                        "children" : [ {
                          "@type" : "C_COMPLEX_OBJECT",
                          "rmTypeName" : "DV_CODED_TEXT",
                          "attributes" : [ {
                            "@type" : "C_ATTRIBUTE",
                            "rmAttributeName" : "defining_code",
                            "children" : [ {
                              "@type" : "C_TERMINOLOGY_CODE",
                              "rmTypeName" : "TERMINOLOGY_CODE",
                              "occurrences" : "1..1",
                              "terminologyId" : {
                                "value" : "local_terms"
                              },
                              "constraint" : [ ],
                              "selectedTerminologies" : [ "local_terms" ],
                              "includedExternalTerminologyCodes" : [ {
                                "terminologyId" : "local_terms",
                                "code" : "0",
                                "value" : "Tidak Pernah"
                              }, {
                                "terminologyId" : "local_terms",
                                "code" : "1",
                                "value" : "Selalu sepanjang hari"
                              }, {
                                "terminologyId" : "local_terms",
                                "code" : "2",
                                "value" : "Sebagian besar hari"
                              }, {
                                "terminologyId" : "local_terms",
                                "code" : "3",
                                "value" : "Separuh Hari"
                              }, {
                                "terminologyId" : "local_terms",
                                "code" : "4",
                                "value" : "Kadang-kadang"
                              } ]
                            } ]
                          } ],
                          "attributeTuples" : [ ]
                        } ]
                      } ],
                      "attributeTuples" : [ ]
                    }, {
                      "@type" : "C_COMPLEX_OBJECT",
                      "rmTypeName" : "ELEMENT",
                      "occurrences" : "1..1",
                      "nodeId" : "at0028.7",
                      "attributes" : [ {
                        "@type" : "C_ATTRIBUTE",
                        "rmAttributeName" : "value",
                        "children" : [ {
                          "@type" : "C_COMPLEX_OBJECT",
                          "rmTypeName" : "DV_CODED_TEXT",
                          "attributes" : [ {
                            "@type" : "C_ATTRIBUTE",
                            "rmAttributeName" : "defining_code",
                            "children" : [ {
                              "@type" : "C_TERMINOLOGY_CODE",
                              "rmTypeName" : "TERMINOLOGY_CODE",
                              "occurrences" : "1..1",
                              "terminologyId" : {
                                "value" : "local_terms"
                              },
                              "constraint" : [ ],
                              "selectedTerminologies" : [ "local_terms" ],
                              "includedExternalTerminologyCodes" : [ {
                                "terminologyId" : "local_terms",
                                "code" : "0",
                                "value" : "Tidak Pernah"
                              }, {
                                "terminologyId" : "local_terms",
                                "code" : "1",
                                "value" : "Selalu sepanjang hari"
                              }, {
                                "terminologyId" : "local_terms",
                                "code" : "2",
                                "value" : "Sebagian besar hari"
                              }, {
                                "terminologyId" : "local_terms",
                                "code" : "3",
                                "value" : "Separuh Hari"
                              }, {
                                "terminologyId" : "local_terms",
                                "code" : "4",
                                "value" : "Kadang-kadang"
                              } ]
                            } ]
                          } ],
                          "attributeTuples" : [ ]
                        } ]
                      } ],
                      "attributeTuples" : [ ]
                    }, {
                      "@type" : "C_COMPLEX_OBJECT",
                      "rmTypeName" : "ELEMENT",
                      "occurrences" : "1..1",
                      "nodeId" : "at0028.8",
                      "attributes" : [ {
                        "@type" : "C_ATTRIBUTE",
                        "rmAttributeName" : "value",
                        "children" : [ {
                          "@type" : "C_COMPLEX_OBJECT",
                          "rmTypeName" : "DV_CODED_TEXT",
                          "attributes" : [ {
                            "@type" : "C_ATTRIBUTE",
                            "rmAttributeName" : "defining_code",
                            "children" : [ {
                              "@type" : "C_TERMINOLOGY_CODE",
                              "rmTypeName" : "TERMINOLOGY_CODE",
                              "occurrences" : "1..1",
                              "terminologyId" : {
                                "value" : "local_terms"
                              },
                              "constraint" : [ ],
                              "selectedTerminologies" : [ "local_terms" ],
                              "includedExternalTerminologyCodes" : [ {
                                "terminologyId" : "local_terms",
                                "code" : "0",
                                "value" : "Tidak Pernah"
                              }, {
                                "terminologyId" : "local_terms",
                                "code" : "1",
                                "value" : "Selalu sepanjang hari"
                              }, {
                                "terminologyId" : "local_terms",
                                "code" : "2",
                                "value" : "Sebagian besar hari"
                              }, {
                                "terminologyId" : "local_terms",
                                "code" : "3",
                                "value" : "Separuh Hari"
                              }, {
                                "terminologyId" : "local_terms",
                                "code" : "4",
                                "value" : "Kadang-kadang"
                              } ]
                            } ]
                          } ],
                          "attributeTuples" : [ ]
                        } ]
                      } ],
                      "attributeTuples" : [ ]
                    }, {
                      "@type" : "C_COMPLEX_OBJECT",
                      "rmTypeName" : "ELEMENT",
                      "occurrences" : "0..0",
                      "nodeId" : "at0029.1",
                      "attributes" : [ {
                        "@type" : "C_ATTRIBUTE",
                        "rmAttributeName" : "value",
                        "children" : [ {
                          "@type" : "C_COMPLEX_OBJECT",
                          "rmTypeName" : "DV_DATE_TIME",
                          "attributes" : [ ],
                          "attributeTuples" : [ ]
                        }, {
                          "@type" : "C_COMPLEX_OBJECT",
                          "rmTypeName" : "DV_INTERVAL<DV_DATE_TIME>",
                          "attributes" : [ ],
                          "attributeTuples" : [ ]
                        }, {
                          "@type" : "C_COMPLEX_OBJECT",
                          "rmTypeName" : "DV_TEXT",
                          "attributes" : [ ],
                          "attributeTuples" : [ ]
                        }, {
                          "@type" : "C_COMPLEX_OBJECT",
                          "rmTypeName" : "DV_DURATION",
                          "attributes" : [ ],
                          "attributeTuples" : [ ]
                        }, {
                          "@type" : "C_COMPLEX_OBJECT",
                          "rmTypeName" : "DV_INTERVAL<DV_DURATION>",
                          "attributes" : [ ],
                          "attributeTuples" : [ ]
                        } ]
                      } ],
                      "attributeTuples" : [ ]
                    }, {
                      "@type" : "C_COMPLEX_OBJECT",
                      "rmTypeName" : "ELEMENT",
                      "occurrences" : "0..0",
                      "nodeId" : "at0036.1",
                      "attributes" : [ ],
                      "attributeTuples" : [ ]
                    }, {
                      "@type" : "C_COMPLEX_OBJECT",
                      "rmTypeName" : "CLUSTER",
                      "occurrences" : "0..0",
                      "nodeId" : "at0022.1",
                      "attributes" : [ {
                        "@type" : "C_ATTRIBUTE",
                        "rmAttributeName" : "items",
                        "children" : [ {
                          "@type" : "C_COMPLEX_OBJECT",
                          "rmTypeName" : "ELEMENT",
                          "occurrences" : "0..0",
                          "nodeId" : "at0005.1",
                          "attributes" : [ {
                            "@type" : "C_ATTRIBUTE",
                            "rmAttributeName" : "value",
                            "children" : [ {
                              "@type" : "C_COMPLEX_OBJECT",
                              "rmTypeName" : "DV_CODED_TEXT",
                              "attributes" : [ {
                                "@type" : "C_ATTRIBUTE",
                                "rmAttributeName" : "defining_code",
                                "children" : [ {
                                  "@type" : "C_TERMINOLOGY_CODE",
                                  "rmTypeName" : "CODE_PHRASE",
                                  "occurrences" : "1..1",
                                  "terminologyId" : {
                                    "value" : "local"
                                  },
                                  "constraint" : [ "at0023", "at0024", "at0027" ]
                                } ]
                              } ],
                              "attributeTuples" : [ ]
                            }, {
                              "@type" : "C_COMPLEX_OBJECT",
                              "rmTypeName" : "DV_TEXT",
                              "attributes" : [ ],
                              "attributeTuples" : [ ]
                            }, {
                              "@type" : "C_COMPLEX_OBJECT",
                              "rmTypeName" : "DV_BOOLEAN",
                              "attributes" : [ ],
                              "attributeTuples" : [ ]
                            } ]
                          } ],
                          "attributeTuples" : [ ]
                        }, {
                          "@type" : "C_COMPLEX_OBJECT",
                          "rmTypeName" : "ELEMENT",
                          "occurrences" : "0..0",
                          "nodeId" : "at0037.1",
                          "attributes" : [ {
                            "@type" : "C_ATTRIBUTE",
                            "rmAttributeName" : "value",
                            "children" : [ {
                              "@type" : "C_COMPLEX_OBJECT",
                              "rmTypeName" : "DV_DURATION",
                              "attributes" : [ ],
                              "attributeTuples" : [ ]
                            }, {
                              "@type" : "C_COMPLEX_OBJECT",
                              "rmTypeName" : "DV_INTERVAL<DV_DURATION>",
                              "attributes" : [ ],
                              "attributeTuples" : [ ]
                            }, {
                              "@type" : "C_COMPLEX_OBJECT",
                              "rmTypeName" : "DV_DATE_TIME",
                              "attributes" : [ ],
                              "attributeTuples" : [ ]
                            }, {
                              "@type" : "C_COMPLEX_OBJECT",
                              "rmTypeName" : "DV_INTERVAL<DV_DATE_TIME>",
                              "attributes" : [ ],
                              "attributeTuples" : [ ]
                            }, {
                              "@type" : "C_COMPLEX_OBJECT",
                              "rmTypeName" : "DV_TEXT",
                              "attributes" : [ ],
                              "attributeTuples" : [ ]
                            } ]
                          } ],
                          "attributeTuples" : [ ]
                        }, {
                          "@type" : "C_COMPLEX_OBJECT",
                          "rmTypeName" : "ELEMENT",
                          "occurrences" : "0..0",
                          "nodeId" : "at0035.1",
                          "attributes" : [ ],
                          "attributeTuples" : [ ]
                        } ]
                      } ],
                      "attributeTuples" : [ ]
                    } ]
                  } ],
                  "attributeTuples" : [ ]
                } ]
              } ],
              "attributeTuples" : [ ]
            } ]
          } ],
          "attributeTuples" : [ ]
        } ]
      } ],
      "attributeTuples" : [ ]
    },
    "terminology" : {
      "@type" : "ARCHETYPE_TERMINOLOGY",
      "conceptCode" : "at0000",
      "termDefinitions" : {
        "en" : {
          "at0028.1" : {
            "@type" : "ARCHETYPE_TERM",
            "code" : "at0028.1",
            "text" : "Mata sensitif terhadap cahaya",
            "description" : "Is there a history of any symptoms or signs relevant for the screening purpose?",
            "comment" : "In a template, the data element would usually be renamed to the specific question asked. The proposed value set can be adapted for local use by using the DV_TEXT or the DV_BOOLEAN datatypes choice to match each specific use case."
          },
          "at0028.2" : {
            "@type" : "ARCHETYPE_TERM",
            "code" : "at0028.2",
            "text" : "Mata terasa mengganjal atau berpasir",
            "description" : "Is there a history of any symptoms or signs relevant for the screening purpose?",
            "comment" : "In a template, the data element would usually be renamed to the specific question asked. The proposed value set can be adapted for local use by using the DV_TEXT or the DV_BOOLEAN datatypes choice to match each specific use case."
          },
          "at0028.3" : {
            "@type" : "ARCHETYPE_TERM",
            "code" : "at0028.3",
            "text" : "Gangguan penglihat berat?",
            "description" : "Is there a history of any symptoms or signs relevant for the screening purpose?",
            "comment" : "In a template, the data element would usually be renamed to the specific question asked. The proposed value set can be adapted for local use by using the DV_TEXT or the DV_BOOLEAN datatypes choice to match each specific use case."
          },
          "at0028.4" : {
            "@type" : "ARCHETYPE_TERM",
            "code" : "at0028.4",
            "text" : "Kesulitan membaca",
            "description" : "Is there a history of any symptoms or signs relevant for the screening purpose?",
            "comment" : "In a template, the data element would usually be renamed to the specific question asked. The proposed value set can be adapted for local use by using the DV_TEXT or the DV_BOOLEAN datatypes choice to match each specific use case."
          },
          "at0028.5" : {
            "@type" : "ARCHETYPE_TERM",
            "code" : "at0028.5",
            "text" : "Kesulitan mengenderai kendaraan di malam hari",
            "description" : "Is there a history of any symptoms or signs relevant for the screening purpose?",
            "comment" : "In a template, the data element would usually be renamed to the specific question asked. The proposed value set can be adapted for local use by using the DV_TEXT or the DV_BOOLEAN datatypes choice to match each specific use case."
          },
          "at0028.6" : {
            "@type" : "ARCHETYPE_TERM",
            "code" : "at0028.6",
            "text" : "Kesulitan menonton televisi",
            "description" : "Is there a history of any symptoms or signs relevant for the screening purpose?",
            "comment" : "In a template, the data element would usually be renamed to the specific question asked. The proposed value set can be adapted for local use by using the DV_TEXT or the DV_BOOLEAN datatypes choice to match each specific use case."
          },
          "at0028.7" : {
            "@type" : "ARCHETYPE_TERM",
            "code" : "at0028.7",
            "text" : "Mata tidak nyaman di tempat atau ruangan dengan kelembaban rendah (sangat kering)?",
            "description" : "Is there a history of any symptoms or signs relevant for the screening purpose?",
            "comment" : "In a template, the data element would usually be renamed to the specific question asked. The proposed value set can be adapted for local use by using the DV_TEXT or the DV_BOOLEAN datatypes choice to match each specific use case."
          },
          "at0028.8" : {
            "@type" : "ARCHETYPE_TERM",
            "code" : "at0028.8",
            "text" : "Mata tidak nyaman di tempat dengan pendingin ruangan",
            "description" : "Is there a history of any symptoms or signs relevant for the screening purpose?",
            "comment" : "In a template, the data element would usually be renamed to the specific question asked. The proposed value set can be adapted for local use by using the DV_TEXT or the DV_BOOLEAN datatypes choice to match each specific use case."
          }
        },
        "fi" : {
          "at0028.2" : {
            "@type" : "ARCHETYPE_TERM",
            "code" : "at0028.1",
            "text" : "*Any symptoms or signs? (en) (2)",
            "description" : "*Is there a history of any symptoms or signs relatevant for the screening purpose? (en)",
            "comment" : "*In a template, the data element would usually be renamed to the specific question asked. The proposed value set can be adapted for local use by using the DV_TEXT or the DV_BOOLEAN datatypes choice to match each specific use case. (en)"
          },
          "at0028.3" : {
            "@type" : "ARCHETYPE_TERM",
            "code" : "at0028.1",
            "text" : "*Any symptoms or signs? (en) (3)",
            "description" : "*Is there a history of any symptoms or signs relatevant for the screening purpose? (en)",
            "comment" : "*In a template, the data element would usually be renamed to the specific question asked. The proposed value set can be adapted for local use by using the DV_TEXT or the DV_BOOLEAN datatypes choice to match each specific use case. (en)"
          },
          "at0028.4" : {
            "@type" : "ARCHETYPE_TERM",
            "code" : "at0028.1",
            "text" : "*Any symptoms or signs? (en) (4)",
            "description" : "*Is there a history of any symptoms or signs relatevant for the screening purpose? (en)",
            "comment" : "*In a template, the data element would usually be renamed to the specific question asked. The proposed value set can be adapted for local use by using the DV_TEXT or the DV_BOOLEAN datatypes choice to match each specific use case. (en)"
          },
          "at0028.5" : {
            "@type" : "ARCHETYPE_TERM",
            "code" : "at0028.1",
            "text" : "*Any symptoms or signs? (en) (5)",
            "description" : "*Is there a history of any symptoms or signs relatevant for the screening purpose? (en)",
            "comment" : "*In a template, the data element would usually be renamed to the specific question asked. The proposed value set can be adapted for local use by using the DV_TEXT or the DV_BOOLEAN datatypes choice to match each specific use case. (en)"
          },
          "at0028.6" : {
            "@type" : "ARCHETYPE_TERM",
            "code" : "at0028.1",
            "text" : "*Any symptoms or signs? (en) (6)",
            "description" : "*Is there a history of any symptoms or signs relatevant for the screening purpose? (en)",
            "comment" : "*In a template, the data element would usually be renamed to the specific question asked. The proposed value set can be adapted for local use by using the DV_TEXT or the DV_BOOLEAN datatypes choice to match each specific use case. (en)"
          },
          "at0028.7" : {
            "@type" : "ARCHETYPE_TERM",
            "code" : "at0028.1",
            "text" : "*Any symptoms or signs? (en) (7)",
            "description" : "*Is there a history of any symptoms or signs relatevant for the screening purpose? (en)",
            "comment" : "*In a template, the data element would usually be renamed to the specific question asked. The proposed value set can be adapted for local use by using the DV_TEXT or the DV_BOOLEAN datatypes choice to match each specific use case. (en)"
          },
          "at0028.8" : {
            "@type" : "ARCHETYPE_TERM",
            "code" : "at0028.1",
            "text" : "*Any symptoms or signs? (en) (8)",
            "description" : "*Is there a history of any symptoms or signs relatevant for the screening purpose? (en)",
            "comment" : "*In a template, the data element would usually be renamed to the specific question asked. The proposed value set can be adapted for local use by using the DV_TEXT or the DV_BOOLEAN datatypes choice to match each specific use case. (en)"
          }
        },
        "nb" : {
          "at0028.2" : {
            "@type" : "ARCHETYPE_TERM",
            "code" : "at0028.1",
            "text" : "Symptomer eller sykdomstegn? (2)",
            "description" : "Finnes det noen tidligere symptomer eller sykdomstegn som er innenfor kartleggingsformålet?",
            "comment" : "Navnet på dataelementet kan omformuleres til det spesifikke spørsmålet i et templat eller brukergrensesnitt. Det foreslåtte verdisettet kan tilpasses/endres i det enkelte bruksområde ved å benytte de alternative datatypene DV_TEXT eller DV_BOOLEAN."
          },
          "at0028.3" : {
            "@type" : "ARCHETYPE_TERM",
            "code" : "at0028.1",
            "text" : "Symptomer eller sykdomstegn? (3)",
            "description" : "Finnes det noen tidligere symptomer eller sykdomstegn som er innenfor kartleggingsformålet?",
            "comment" : "Navnet på dataelementet kan omformuleres til det spesifikke spørsmålet i et templat eller brukergrensesnitt. Det foreslåtte verdisettet kan tilpasses/endres i det enkelte bruksområde ved å benytte de alternative datatypene DV_TEXT eller DV_BOOLEAN."
          },
          "at0028.4" : {
            "@type" : "ARCHETYPE_TERM",
            "code" : "at0028.1",
            "text" : "Symptomer eller sykdomstegn? (4)",
            "description" : "Finnes det noen tidligere symptomer eller sykdomstegn som er innenfor kartleggingsformålet?",
            "comment" : "Navnet på dataelementet kan omformuleres til det spesifikke spørsmålet i et templat eller brukergrensesnitt. Det foreslåtte verdisettet kan tilpasses/endres i det enkelte bruksområde ved å benytte de alternative datatypene DV_TEXT eller DV_BOOLEAN."
          },
          "at0028.5" : {
            "@type" : "ARCHETYPE_TERM",
            "code" : "at0028.1",
            "text" : "Symptomer eller sykdomstegn? (5)",
            "description" : "Finnes det noen tidligere symptomer eller sykdomstegn som er innenfor kartleggingsformålet?",
            "comment" : "Navnet på dataelementet kan omformuleres til det spesifikke spørsmålet i et templat eller brukergrensesnitt. Det foreslåtte verdisettet kan tilpasses/endres i det enkelte bruksområde ved å benytte de alternative datatypene DV_TEXT eller DV_BOOLEAN."
          },
          "at0028.6" : {
            "@type" : "ARCHETYPE_TERM",
            "code" : "at0028.1",
            "text" : "Symptomer eller sykdomstegn? (6)",
            "description" : "Finnes det noen tidligere symptomer eller sykdomstegn som er innenfor kartleggingsformålet?",
            "comment" : "Navnet på dataelementet kan omformuleres til det spesifikke spørsmålet i et templat eller brukergrensesnitt. Det foreslåtte verdisettet kan tilpasses/endres i det enkelte bruksområde ved å benytte de alternative datatypene DV_TEXT eller DV_BOOLEAN."
          },
          "at0028.7" : {
            "@type" : "ARCHETYPE_TERM",
            "code" : "at0028.1",
            "text" : "Symptomer eller sykdomstegn? (7)",
            "description" : "Finnes det noen tidligere symptomer eller sykdomstegn som er innenfor kartleggingsformålet?",
            "comment" : "Navnet på dataelementet kan omformuleres til det spesifikke spørsmålet i et templat eller brukergrensesnitt. Det foreslåtte verdisettet kan tilpasses/endres i det enkelte bruksområde ved å benytte de alternative datatypene DV_TEXT eller DV_BOOLEAN."
          },
          "at0028.8" : {
            "@type" : "ARCHETYPE_TERM",
            "code" : "at0028.1",
            "text" : "Symptomer eller sykdomstegn? (8)",
            "description" : "Finnes det noen tidligere symptomer eller sykdomstegn som er innenfor kartleggingsformålet?",
            "comment" : "Navnet på dataelementet kan omformuleres til det spesifikke spørsmålet i et templat eller brukergrensesnitt. Det foreslåtte verdisettet kan tilpasses/endres i det enkelte bruksområde ved å benytte de alternative datatypene DV_TEXT eller DV_BOOLEAN."
          }
        },
        "de" : {
          "at0028.2" : {
            "@type" : "ARCHETYPE_TERM",
            "code" : "at0028.1",
            "text" : "*Any symptoms or signs? (en) (2)",
            "description" : "*Is there a history of any symptoms or signs relatevant for the screening purpose? (en)",
            "comment" : "*In a template, the data element would usually be renamed to the specific question asked. The proposed value set can be adapted for local use by using the DV_TEXT or the DV_BOOLEAN datatypes choice to match each specific use case. (en)"
          },
          "at0028.3" : {
            "@type" : "ARCHETYPE_TERM",
            "code" : "at0028.1",
            "text" : "*Any symptoms or signs? (en) (3)",
            "description" : "*Is there a history of any symptoms or signs relatevant for the screening purpose? (en)",
            "comment" : "*In a template, the data element would usually be renamed to the specific question asked. The proposed value set can be adapted for local use by using the DV_TEXT or the DV_BOOLEAN datatypes choice to match each specific use case. (en)"
          },
          "at0028.4" : {
            "@type" : "ARCHETYPE_TERM",
            "code" : "at0028.1",
            "text" : "*Any symptoms or signs? (en) (4)",
            "description" : "*Is there a history of any symptoms or signs relatevant for the screening purpose? (en)",
            "comment" : "*In a template, the data element would usually be renamed to the specific question asked. The proposed value set can be adapted for local use by using the DV_TEXT or the DV_BOOLEAN datatypes choice to match each specific use case. (en)"
          },
          "at0028.5" : {
            "@type" : "ARCHETYPE_TERM",
            "code" : "at0028.1",
            "text" : "*Any symptoms or signs? (en) (5)",
            "description" : "*Is there a history of any symptoms or signs relatevant for the screening purpose? (en)",
            "comment" : "*In a template, the data element would usually be renamed to the specific question asked. The proposed value set can be adapted for local use by using the DV_TEXT or the DV_BOOLEAN datatypes choice to match each specific use case. (en)"
          },
          "at0028.6" : {
            "@type" : "ARCHETYPE_TERM",
            "code" : "at0028.1",
            "text" : "*Any symptoms or signs? (en) (6)",
            "description" : "*Is there a history of any symptoms or signs relatevant for the screening purpose? (en)",
            "comment" : "*In a template, the data element would usually be renamed to the specific question asked. The proposed value set can be adapted for local use by using the DV_TEXT or the DV_BOOLEAN datatypes choice to match each specific use case. (en)"
          },
          "at0028.7" : {
            "@type" : "ARCHETYPE_TERM",
            "code" : "at0028.1",
            "text" : "*Any symptoms or signs? (en) (7)",
            "description" : "*Is there a history of any symptoms or signs relatevant for the screening purpose? (en)",
            "comment" : "*In a template, the data element would usually be renamed to the specific question asked. The proposed value set can be adapted for local use by using the DV_TEXT or the DV_BOOLEAN datatypes choice to match each specific use case. (en)"
          },
          "at0028.8" : {
            "@type" : "ARCHETYPE_TERM",
            "code" : "at0028.1",
            "text" : "*Any symptoms or signs? (en) (8)",
            "description" : "*Is there a history of any symptoms or signs relatevant for the screening purpose? (en)",
            "comment" : "*In a template, the data element would usually be renamed to the specific question asked. The proposed value set can be adapted for local use by using the DV_TEXT or the DV_BOOLEAN datatypes choice to match each specific use case. (en)"
          }
        },
        "it" : {
          "at0028.2" : {
            "@type" : "ARCHETYPE_TERM",
            "code" : "at0028.1",
            "text" : "*Any symptoms or signs? (en) (2)",
            "description" : "*Is there a history of any symptoms or signs relatevant for the screening purpose? (en)",
            "comment" : "*In a template, the data element would usually be renamed to the specific question asked. The proposed value set can be adapted for local use by using the DV_TEXT or the DV_BOOLEAN datatypes choice to match each specific use case. (en)"
          },
          "at0028.3" : {
            "@type" : "ARCHETYPE_TERM",
            "code" : "at0028.1",
            "text" : "*Any symptoms or signs? (en) (3)",
            "description" : "*Is there a history of any symptoms or signs relatevant for the screening purpose? (en)",
            "comment" : "*In a template, the data element would usually be renamed to the specific question asked. The proposed value set can be adapted for local use by using the DV_TEXT or the DV_BOOLEAN datatypes choice to match each specific use case. (en)"
          },
          "at0028.4" : {
            "@type" : "ARCHETYPE_TERM",
            "code" : "at0028.1",
            "text" : "*Any symptoms or signs? (en) (4)",
            "description" : "*Is there a history of any symptoms or signs relatevant for the screening purpose? (en)",
            "comment" : "*In a template, the data element would usually be renamed to the specific question asked. The proposed value set can be adapted for local use by using the DV_TEXT or the DV_BOOLEAN datatypes choice to match each specific use case. (en)"
          },
          "at0028.5" : {
            "@type" : "ARCHETYPE_TERM",
            "code" : "at0028.1",
            "text" : "*Any symptoms or signs? (en) (5)",
            "description" : "*Is there a history of any symptoms or signs relatevant for the screening purpose? (en)",
            "comment" : "*In a template, the data element would usually be renamed to the specific question asked. The proposed value set can be adapted for local use by using the DV_TEXT or the DV_BOOLEAN datatypes choice to match each specific use case. (en)"
          },
          "at0028.6" : {
            "@type" : "ARCHETYPE_TERM",
            "code" : "at0028.1",
            "text" : "*Any symptoms or signs? (en) (6)",
            "description" : "*Is there a history of any symptoms or signs relatevant for the screening purpose? (en)",
            "comment" : "*In a template, the data element would usually be renamed to the specific question asked. The proposed value set can be adapted for local use by using the DV_TEXT or the DV_BOOLEAN datatypes choice to match each specific use case. (en)"
          },
          "at0028.7" : {
            "@type" : "ARCHETYPE_TERM",
            "code" : "at0028.1",
            "text" : "*Any symptoms or signs? (en) (7)",
            "description" : "*Is there a history of any symptoms or signs relatevant for the screening purpose? (en)",
            "comment" : "*In a template, the data element would usually be renamed to the specific question asked. The proposed value set can be adapted for local use by using the DV_TEXT or the DV_BOOLEAN datatypes choice to match each specific use case. (en)"
          },
          "at0028.8" : {
            "@type" : "ARCHETYPE_TERM",
            "code" : "at0028.1",
            "text" : "*Any symptoms or signs? (en) (8)",
            "description" : "*Is there a history of any symptoms or signs relatevant for the screening purpose? (en)",
            "comment" : "*In a template, the data element would usually be renamed to the specific question asked. The proposed value set can be adapted for local use by using the DV_TEXT or the DV_BOOLEAN datatypes choice to match each specific use case. (en)"
          }
        },
        "sv" : {
          "at0028.2" : {
            "@type" : "ARCHETYPE_TERM",
            "code" : "at0028.1",
            "text" : "*Any symptoms or signs? (en) (2)",
            "description" : "*Is there a history of any symptoms or signs relatevant for the screening purpose? (en)",
            "comment" : "*In a template, the data element would usually be renamed to the specific question asked. The proposed value set can be adapted for local use by using the DV_TEXT or the DV_BOOLEAN datatypes choice to match each specific use case. (en)"
          },
          "at0028.3" : {
            "@type" : "ARCHETYPE_TERM",
            "code" : "at0028.1",
            "text" : "*Any symptoms or signs? (en) (3)",
            "description" : "*Is there a history of any symptoms or signs relatevant for the screening purpose? (en)",
            "comment" : "*In a template, the data element would usually be renamed to the specific question asked. The proposed value set can be adapted for local use by using the DV_TEXT or the DV_BOOLEAN datatypes choice to match each specific use case. (en)"
          },
          "at0028.4" : {
            "@type" : "ARCHETYPE_TERM",
            "code" : "at0028.1",
            "text" : "*Any symptoms or signs? (en) (4)",
            "description" : "*Is there a history of any symptoms or signs relatevant for the screening purpose? (en)",
            "comment" : "*In a template, the data element would usually be renamed to the specific question asked. The proposed value set can be adapted for local use by using the DV_TEXT or the DV_BOOLEAN datatypes choice to match each specific use case. (en)"
          },
          "at0028.5" : {
            "@type" : "ARCHETYPE_TERM",
            "code" : "at0028.1",
            "text" : "*Any symptoms or signs? (en) (5)",
            "description" : "*Is there a history of any symptoms or signs relatevant for the screening purpose? (en)",
            "comment" : "*In a template, the data element would usually be renamed to the specific question asked. The proposed value set can be adapted for local use by using the DV_TEXT or the DV_BOOLEAN datatypes choice to match each specific use case. (en)"
          },
          "at0028.6" : {
            "@type" : "ARCHETYPE_TERM",
            "code" : "at0028.1",
            "text" : "*Any symptoms or signs? (en) (6)",
            "description" : "*Is there a history of any symptoms or signs relatevant for the screening purpose? (en)",
            "comment" : "*In a template, the data element would usually be renamed to the specific question asked. The proposed value set can be adapted for local use by using the DV_TEXT or the DV_BOOLEAN datatypes choice to match each specific use case. (en)"
          },
          "at0028.7" : {
            "@type" : "ARCHETYPE_TERM",
            "code" : "at0028.1",
            "text" : "*Any symptoms or signs? (en) (7)",
            "description" : "*Is there a history of any symptoms or signs relatevant for the screening purpose? (en)",
            "comment" : "*In a template, the data element would usually be renamed to the specific question asked. The proposed value set can be adapted for local use by using the DV_TEXT or the DV_BOOLEAN datatypes choice to match each specific use case. (en)"
          },
          "at0028.8" : {
            "@type" : "ARCHETYPE_TERM",
            "code" : "at0028.1",
            "text" : "*Any symptoms or signs? (en) (8)",
            "description" : "*Is there a history of any symptoms or signs relatevant for the screening purpose? (en)",
            "comment" : "*In a template, the data element would usually be renamed to the specific question asked. The proposed value set can be adapted for local use by using the DV_TEXT or the DV_BOOLEAN datatypes choice to match each specific use case. (en)"
          }
        }
      },
      "termBindings" : { },
      "terminologyExtracts" : { },
      "valueSets" : {
        "ac0.1" : {
          "@type" : "VALUE_SET",
          "id" : "ac0.1",
          "members" : [ "at0031", "at0032", "at0033" ]
        },
        "ac0.3" : {
          "@type" : "VALUE_SET",
          "id" : "ac0.3",
          "members" : [ "at0031", "at0032", "at0033" ]
        },
        "ac0.4" : {
          "@type" : "VALUE_SET",
          "id" : "ac0.4",
          "members" : [ ]
        },
        "ac0.5" : {
          "@type" : "VALUE_SET",
          "id" : "ac0.5",
          "members" : [ ]
        }
      }
    },
    "adlVersion" : "1.4",
    "buildUid" : "b265bd06-044d-4245-9864-f97e297821c5",
    "rmName" : "openehr",
    "rmRelease" : "1.1.0",
    "generated" : true,
    "otherMetaData" : { },
    "originalLanguage" : {
      "terminologyId" : {
        "value" : "ISO_639-1"
      },
      "codeString" : "en"
    },
    "translations" : [ {
      "@type" : "TRANSLATION_DETAILS",
      "language" : {
        "terminologyId" : {
          "value" : "ISO_639-1"
        },
        "codeString" : "de"
      },
      "author" : {
        "name" : "Sarah Ballout, Natalia Strauch",
        "organisation" : "Medizinische Hochschule Hannover",
        "email" : "ballout.sarah@mh-hannover.de, Strauch.Natalia@mh-hannover.de"
      },
      "otherDetails" : { }
    }, {
      "@type" : "TRANSLATION_DETAILS",
      "language" : {
        "terminologyId" : {
          "value" : "ISO_639-1"
        },
        "codeString" : "fi"
      },
      "author" : { },
      "otherDetails" : { }
    }, {
      "@type" : "TRANSLATION_DETAILS",
      "language" : {
        "terminologyId" : {
          "value" : "ISO_639-1"
        },
        "codeString" : "sv"
      },
      "author" : {
        "name" : "Emma Malm, Erik Sundvall",
        "organisation" : "Karolinska University Hospital, Region Stockholm, Karolinska University Hospital, Region Stockholm + Linköping University",
        "email" : "emma.malm@cambio.se, erik.sundvall@regionstockholm.se"
      },
      "otherDetails" : { }
    }, {
      "@type" : "TRANSLATION_DETAILS",
      "language" : {
        "terminologyId" : {
          "value" : "ISO_639-1"
        },
        "codeString" : "nb"
      },
      "author" : {
        "name" : "Marit Alice Venheim, Silje Ljosland Bakke, John Tore Valand",
        "organisation" : "Helse Vest IKT AS, Helse Bergen",
        "email" : "marit.alice.venheim@helse-vest-ikt.no, silje.ljosland.bakke@helse-vest-ikt.no, john.tore.valand@helse-vest-ikt.no"
      },
      "otherDetails" : { }
    }, {
      "@type" : "TRANSLATION_DETAILS",
      "language" : {
        "terminologyId" : {
          "value" : "ISO_639-1"
        },
        "codeString" : "it"
      },
      "author" : { },
      "otherDetails" : { }
    } ]
  } ],
  "originalLanguage" : {
    "terminologyId" : {
      "value" : "ISO_639-1"
    },
    "codeString" : "en"
  },
  "translations" : [ {
    "@type" : "TRANSLATION_DETAILS",
    "language" : {
      "terminologyId" : {
        "value" : "ISO_639-1"
      },
      "codeString" : "de"
    },
    "author" : { },
    "otherDetails" : { }
  }, {
    "@type" : "TRANSLATION_DETAILS",
    "language" : {
      "terminologyId" : {
        "value" : "ISO_639-1"
      },
      "codeString" : "ru"
    },
    "author" : { },
    "otherDetails" : { }
  }, {
    "@type" : "TRANSLATION_DETAILS",
    "language" : {
      "terminologyId" : {
        "value" : "ISO_639-1"
      },
      "codeString" : "sv"
    },
    "author" : { },
    "otherDetails" : { }
  }, {
    "@type" : "TRANSLATION_DETAILS",
    "language" : {
      "terminologyId" : {
        "value" : "ISO_639-1"
      },
      "codeString" : "es-ar"
    },
    "author" : { },
    "otherDetails" : { }
  }, {
    "@type" : "TRANSLATION_DETAILS",
    "language" : {
      "terminologyId" : {
        "value" : "ISO_639-1"
      },
      "codeString" : "nb"
    },
    "author" : { },
    "otherDetails" : { }
  }, {
    "@type" : "TRANSLATION_DETAILS",
    "language" : {
      "terminologyId" : {
        "value" : "ISO_639-1"
      },
      "codeString" : "pt-br"
    },
    "author" : { },
    "otherDetails" : { }
  }, {
    "@type" : "TRANSLATION_DETAILS",
    "language" : {
      "terminologyId" : {
        "value" : "ISO_639-1"
      },
      "codeString" : "sl"
    },
    "author" : { },
    "otherDetails" : { }
  }, {
    "@type" : "TRANSLATION_DETAILS",
    "language" : {
      "terminologyId" : {
        "value" : "ISO_639-1"
      },
      "codeString" : "it"
    },
    "author" : { },
    "otherDetails" : { }
  }, {
    "@type" : "TRANSLATION_DETAILS",
    "language" : {
      "terminologyId" : {
        "value" : "ISO_639-1"
      },
      "codeString" : "fr"
    },
    "author" : { },
    "otherDetails" : { }
  } ]
}